django_simple_third_party_jwt/__init__.py
django_simple_third_party_jwt/admin.py
django_simple_third_party_jwt/apps.py
django_simple_third_party_jwt/exception.py
django_simple_third_party_jwt/models.py
django_simple_third_party_jwt/settings.py
django_simple_third_party_jwt/tests.py
django_simple_third_party_jwt/urls.py
django_simple_third_party_jwt/migrations/0001_initial.py
django_simple_third_party_jwt/migrations/__init__.py
django_simple_third_party_jwt/serilizers/__init__.py
django_simple_third_party_jwt/serilizers/google_login.py
django_simple_third_party_jwt/templates/microsoft/index.html
django_simple_third_party_jwt/utils/__init__.py
django_simple_third_party_jwt/utils/get_tokens_for_user.py
django_simple_third_party_jwt/utils/third_party_login.py
django_simple_third_party_jwt/views/__init__.py
django_simple_third_party_jwt/views/google/__init__.py
django_simple_third_party_jwt/views/google/login.py
django_simple_third_party_jwt/views/microsoft/__init__.py
django_simple_third_party_jwt/views/microsoft/auth.py
django_simple_third_party_jwt/views/microsoft/msal_helpers.py
django_simple_third_party_jwt/views/microsoft/utils.py
django_simple_third_party_jwt-0.3.1.dist-info/LICENSE
django_simple_third_party_jwt-0.3.1.dist-info/METADATA
django_simple_third_party_jwt-0.3.1.dist-info/WHEEL
django_simple_third_party_jwt-0.3.1.dist-info/top_level.txt
django_simple_third_party_jwt-0.3.1.dist-info/RECORD
