Metadata-Version: 2.1
Name: django-simple-third-party-jwt
Version: 0.3.1
Summary: Easy to use JWT with 3rd party login.
Home-page: https://github.com/NatLee/Django-Simple-3rd-Party-JWT
Author: Nat Lee
Author-email: natlee.work@gmail.com
Project-URL: Documentation, https://github.com/natlee/Django-Simple-3rd-Party-JWT
Project-URL: Bug Reports, https://github.com/natlee/Django-Simple-3rd-Party-JWT/issues
Project-URL: Source Code, https://github.com/natlee/Django-Simple-3rd-Party-JWT
Keywords: django,jwt,3rd party login,microsoft login,google login
Classifier: Development Status :: 5 - Production/Stable
Classifier: Intended Audience :: Developers
Classifier: Topic :: Software Development :: Build Tools
Classifier: Programming Language :: Python :: 3
Classifier: Programming Language :: Python :: 3.8
Classifier: Programming Language :: Python :: 3.9
Classifier: Programming Language :: Python :: 3.10
Classifier: Programming Language :: Python :: 3.11
Classifier: Programming Language :: Python :: 3.12
Classifier: Programming Language :: Python :: 3 :: Only
Classifier: License :: OSI Approved :: MIT License
Classifier: Operating System :: OS Independent
Requires-Python: >=3.8
License-File: LICENSE
Requires-Dist: django>=4.0.0
Requires-Dist: djangorestframework
Requires-Dist: djangorestframework-simplejwt>=5.0.0
Requires-Dist: requests
Requires-Dist: google-auth
Requires-Dist: msal
Provides-Extra: dev
Requires-Dist: check-manifest; extra == "dev"
